dev_tools/__init__.py
dev_tools/algorithms_testing_tools.py
dev_tools/constants.py
dev_tools/model_loading.py
dev_tools/model_size.json
dev_tools/model_test_results.json
dev_tools/model_test_results_v0.json
dev_tools/supported_models.ipynb
dev_tools/test_model.py
dev_tools/testing.py
dev_tools/testing_result_registry.py
dev_tools/timeout.py
dev_tools/update_model_size.py
docker/Dockerfile
docker/build_docker_image_locally.sh
docker/requirements-docker.txt
node_api_conversion/__init__.py
node_api_conversion/convert_cell_to_dag_module.py
node_api_conversion/convert_dag_module_to_cell.py
node_api_conversion/from_nd_converter.py
node_api_conversion/to_nd_converter.py
node_api_conversion/utils.py
node_api_conversion/tests/__init__.py
node_api_conversion/tests/test_conversion_from_nd.py
resources/channel_pruning_supported_models_table.md
resources/conversion_to_dag_module.md
resources/pruning_plots.ipynb
resources/pruning_readme.md
resources/pruning_results.md
resources/supported_models_table.md
resources/examples/mnist_notebook.ipynb
resources/examples/custom_models/swiftformer_example.ipynb
resources/examples/custom_models/swiftformer_example.py
resources/pruning_results_plots/f1.png
resources/pruning_results_plots/f2.png
resources/pruning_results_plots/f3.png
resources/pruning_results_plots/f4.png
resources/pruning_results_plots/f5.png
torch_dag/__init__.py
torch_dag/structured_modules.py
torch_dag/api/__init__.py
torch_dag/api/commons.py
torch_dag/api/core.py
torch_dag/api/io.py
torch_dag/api/patterns.py
torch_dag/api/patterns_v2.py
torch_dag/api/visualization.py
torch_dag/builders/__init__.py
torch_dag/commons/__init__.py
torch_dag/commons/compute_stats.py
torch_dag/commons/dag_processors.py
torch_dag/commons/debugging_tools.py
torch_dag/commons/flops_computation.py
torch_dag/commons/mixins.py
torch_dag/conversion/export_onnx.py
torch_dag/core/__init__.py
torch_dag/core/common_tools.py
torch_dag/core/dag_module.py
torch_dag/core/dag_module_utils.py
torch_dag-0.1.3.dist-info/LICENSE
torch_dag-0.1.3.dist-info/METADATA
torch_dag-0.1.3.dist-info/WHEEL
torch_dag-0.1.3.dist-info/entry_points.txt
torch_dag-0.1.3.dist-info/top_level.txt
torch_dag-0.1.3.dist-info/zip-safe
torch_dag-0.1.3.dist-info/RECORD
