Metadata-Version: 2.1
Name: torch_dag
Version: 0.1.3
Summary: torch-dag is a repository in which we implement a graph-like representation for torch models so that we have a unified structure for every model.
Author: TCL Research Europe
Classifier: Programming Language :: Python :: 3
Requires-Python: >=3.7
License-File: LICENSE
Requires-Dist: click
Requires-Dist: fvcore
Requires-Dist: timm<=0.9.12,>=0.9.5
Requires-Dist: torch<=2.1.2,>=2.1.0
Requires-Dist: tqdm
Requires-Dist: graphviz
Requires-Dist: pyyaml
Requires-Dist: numpy==1.26.3
